Latches/SRlatchusingnandgate.v
module  srlatchgatelevel(input s,r,e, output q,qbar);
    nand(q,s,qbar,e);
    nand(qbar,r,q,e);
endmodule

module srlatchbehaviourmodel (input s,r,e,output reg q,qbar);
    always @(*) begin
        if (e)
        case ({s,r})
            2'b00: {q,qbar}<=2'bxx; //invalid
            2'b01: {q,qbar}<=2'b10; //reset
            2'b10: {q,qbar}<=2'b01; //set
            2'b11: {q,qbar}<={q,qbar}; //hold
            default: {q,qbar}<=2'bxx;
        endcase
        else 
            {q,qbar} <={q,qbar};
    end
endmodule

module srlatchtb;
    reg s,r,e;
    wire q,qbar;
    integer m;
    srlatchbehaviourmodel s1(s,r,e,q,qbar);
    initial begin
        $monitor("%b     %b     %b     %b     %b",e,s,r,q,qbar);
        for (m=0;m<8;m=m+1) begin
            {e,s,r} <= m;
            #1;
        end
    end
    initial begin
        $dumpfile("SRlatchusingnand.vcd");
        $dumpvars(0,srlatchtb);
    end
endmodule

VCDfiles/SRlatchusingnand.vcd
$date
	Fri Aug 14 07:00:07 2026
$end
$version
	Icarus Verilog
$end
$timescale
	1s
$end
$scope module srlatchtb $end
$var wire 1 ! qbar $end
$var wire 1 " q $end
$var reg 1 # e $end
$var reg 1 $ r $end
$var reg 1 % s $end
$var integer 32 & m [31:0] $end
$scope module s1 $end
$var wire 1 # e $end
$var wire 1 $ r $end
$var wire 1 % s $end
$var reg 1 " q $end
$var reg 1 ! qbar $end
$upscope $end
$upscope $end
$enddefinitions $end
#0
$dumpvars
b0 &
0%
0$
0#
x"
x!
$end
#1
1$
b1 &
#2
1%
0$
b10 &
#3
1$
b11 &
#4
1#
0%
0$
b100 &
#5
1"
0!
1$
b101 &
#6
0"
1!
1%
0$
b110 &
#7
1$
b111 &
#8
b1000 &
