Verilog/Basics/fulladderwithtestbench.v
module fulladder(input a,b,cin, output reg s,c);
    always @(*) begin
        s = a^b^cin;
        c = (a&b) | (a&cin) | (b&cin);
    end
endmodule
module tb;
    reg at,bt,cint;
    wire st,ct;
    fulladder fa1(at,bt,cint,st,ct);
    initial begin
        $monitor("a=%b   b=%b   cin=%b      s=%b   c=%b",at,bt,cint,st,ct);
        {at,bt,cint} = 3'b000;
        #1;
        {at,bt,cint} = 3'b001;
        #1;
        {at,bt,cint} = 3'b010;
        #1;
        {at,bt,cint} = 3'b011;
        #1;
        {at,bt,cint} = 3'b100;
        #1;
        {at,bt,cint} = 3'b101;
        #1;
        {at,bt,cint} = 3'b110;
        #1;
        {at,bt,cint} = 3'b111;
        #1;
    end
    initial begin
        $dumpfile("fulladder.vcd");
        $dumpvars(0,tb);
    end
endmodule

Verilog/VCDfiles/fulladder.vcd
$date
	Sat Aug 01 16:13:15 2026
$end
$version
	Icarus Verilog
$end
$timescale
	1s
$end
$scope module tb $end
$var wire 1 ! st $end
$var wire 1 " ct $end
$var reg 1 # at $end
$var reg 1 $ bt $end
$var reg 1 % cint $end
$scope module fa1 $end
$var wire 1 # a $end
$var wire 1 $ b $end
$var wire 1 % cin $end
$var reg 1 " c $end
$var reg 1 ! s $end
$upscope $end
$upscope $end
$enddefinitions $end
#0
$dumpvars
0%
0$
0#
0"
0!
$end
#1
1!
1%
#2
1$
0%
#3
1"
0!
1%
#4
0"
1!
1#
0$
0%
#5
1"
0!
1%
#6
1$
0%
#7
1!
1%
