Verilog/Basics/multiplexer2x1withtestbench.v
module multiplexergatelevelmodel (input s, input [1:0] i, output y);
    wire s0, a,b;
    not (s0,s);
    and(a,s0,i[0]);
    and(b,s,i[1]);
    or(y,a,b);
endmodule

module multiplexerdataflowmodel(input s, input [1:0] i, output y);
    assign y = (i[0]&(!s)) | (i[1]&s);
endmodule

module multiplexerbehaviousmodel(input s,input [1:0] i, output reg y);
    always @(*) begin
    case (s)
        0: y = i[0];
        1: y = i[1]; 
        default: y = 0;
    endcase    
    end
endmodule

module multiplexertb;
    reg s;
    reg [1:0]i;
    wire y;
    multiplexerbehaviousmodel m1(s,i,y);
    integer m;
    initial begin
        $monitor("%b  %b  %b  %b",s,i[0],i[1],y);
       for (m=0;m<8;m=m+1) begin
        {s,i[0],i[1]}=m;
        #1;
       end
    end
    initial begin
        $dumpfile("Multiplexer2x1.vcd");
        $dumpvars(0,multiplexertb);
    end
endmodule

Verilog/VCDfiles/Multiplexer2x1.vcd
$date
	Sat Aug 01 16:12:01 2026
$end
$version
	Icarus Verilog
$end
$timescale
	1s
$end
$scope module multiplexertb $end
$var wire 1 ! y $end
$var reg 2 " i [1:0] $end
$var reg 1 # s $end
$var integer 32 $ m [31:0] $end
$scope module m1 $end
$var wire 2 % i [1:0] $end
$var wire 1 # s $end
$var reg 1 ! y $end
$upscope $end
$upscope $end
$enddefinitions $end
#0
$dumpvars
b0 %
b0 $
0#
b0 "
0!
$end
#1
b10 "
b10 %
b1 $
#2
1!
b1 "
b1 %
b10 $
#3
b11 "
b11 %
b11 $
#4
0!
1#
b0 "
b0 %
b100 $
#5
1!
b10 "
b10 %
b101 $
#6
0!
b1 "
b1 %
b110 $
#7
1!
b11 "
b11 %
b111 $
#8
b1000 $
